rosamllib/__init__.py
rosamllib/compare_dcms.py
rosamllib/constants.py
rosamllib/mask_processing.py
rosamllib/registration.py
rosamllib/utils.py
rosamllib/viewers.py
rosamllib/dicoms/__init__.py
rosamllib/dicoms/dicom_image.py
rosamllib/dicoms/raw.py
rosamllib/dicoms/reg.py
rosamllib/dicoms/rtdose.py
rosamllib/dicoms/rtimage.py
rosamllib/dicoms/rtplan.py
rosamllib/dicoms/rtrecord.py
rosamllib/dicoms/rtstruct.py
rosamllib/dicoms/rtstruct_builder.py
rosamllib/dicoms/seg.py
rosamllib/networking/__init__.py
rosamllib/networking/qr_scu.py
rosamllib/networking/store_scp.py
rosamllib/nodes/__init__.py
rosamllib/nodes/dicom_nodes.py
rosamllib/nodes/query_dicom.py
rosamllib/nodes/visitors.py
rosamllib/readers/__init__.py
rosamllib/readers/dicom_image_reader.py
rosamllib/readers/dicom_loader.py
rosamllib/readers/dicom_nodes.py
rosamllib/readers/dicom_raw_reader.py
rosamllib/readers/plan_reader.py
rosamllib/readers/query_dicom.py
rosamllib/readers/record_reader.py
rosamllib/readers/reg_reader.py
rosamllib/readers/rtdose_reader.py
rosamllib/readers/rtimage_reader.py
rosamllib/readers/rtstruct_reader.py
rosamllib/readers/seg_reader.py
rosamllib/readers/visitors.py
rosamllib/utils/__init__.py
rosamllib/utils/dicom_node_utils.py
rosamllib/utils/dicom_utils.py
rosamllib/utils/imaging_utils.py
rosamllib/utils/networking_utils.py
rosamllib/utils/query_df.py
rosamllib/utils/utils.py
rosamllib-0.5.10.dist-info/licenses/LICENSE
rosamllib-0.5.10.dist-info/METADATA
rosamllib-0.5.10.dist-info/WHEEL
rosamllib-0.5.10.dist-info/top_level.txt
rosamllib-0.5.10.dist-info/RECORD
