Metadata-Version: 2.4
Name: rosamllib
Version: 0.5.10
Summary: A library for reading and processing medical imaging files like DICOM, RTDOSE, RTSTRUCT, etc.
Author-email: Yasin Abdulkadir <YasinAAbdulkadir@gmail.com>
License: LGPL-3.0-only
Requires-Python: >=3.7
License-File: LICENSE
Requires-Dist: graphviz
Requires-Dist: highdicom
Requires-Dist: matplotlib
Requires-Dist: numpy
Requires-Dist: nibabel
Requires-Dist: opencv-python
Requires-Dist: pandas
Requires-Dist: plotly
Requires-Dist: pydicom
Requires-Dist: pynetdicom
Requires-Dist: pyyaml
Requires-Dist: rt-utils==1.2.7
Requires-Dist: scikit-image
Requires-Dist: scipy
Requires-Dist: SimpleITK
Requires-Dist: SQLAlchemy
Requires-Dist: tqdm
Requires-Dist: xmltodict
Dynamic: license-file
